eppy/__init__.py
eppy/bunch_subclass.py
eppy/bunchhelpers.py
eppy/easyopen.py
eppy/eppy.py
eppy/ext_field_functions.py
eppy/fanpower.py
eppy/function_helpers.py
eppy/git_notes.txt
eppy/hvacbuilder.py
eppy/idd_helpers.py
eppy/iddcurrent.py
eppy/iddgaps.py
eppy/iddv7.py
eppy/iddv800.py
eppy/iddv940.py
eppy/idf_helpers.py
eppy/idf_msequence.py
eppy/idfreader.py
eppy/json_functions.py
eppy/loops.py
eppy/modeleditor.py
eppy/notes.txt
eppy/pytest_helpers.py
eppy/roadmap.txt
eppy/runningnotes.txt
eppy/simpleread.py
eppy/simplesurface.py
eppy/snippet.py
eppy/walk_hvac.py
eppy/EPlusInterfaceFunctions/__init__.py
eppy/EPlusInterfaceFunctions/eplusdata.py
eppy/EPlusInterfaceFunctions/iddgroups.py
eppy/EPlusInterfaceFunctions/iddindex.py
eppy/EPlusInterfaceFunctions/mylib1.py
eppy/EPlusInterfaceFunctions/mylib2.py
eppy/EPlusInterfaceFunctions/parse_idd.py
eppy/EPlusInterfaceFunctions/readidf.py
eppy/EPlusInterfaceFunctions/structures.py
eppy/constructions/__init__.py
eppy/constructions/thermal_properties.py
eppy/geometry/__init__.py
eppy/geometry/area_zone.py
eppy/geometry/compressed.idf
eppy/geometry/height_surface.py
eppy/geometry/int2lines.py
eppy/geometry/mcve.py
eppy/geometry/plan.md
eppy/geometry/surface.py
eppy/geometry/volume_zone.py
eppy/resources/iddfiles/Energy+V1_1.idd
eppy/resources/iddfiles/Energy+V6_0.idd
eppy/resources/iddfiles/Energy+V7_0_0_036.idd
eppy/resources/iddfiles/Energy+V7_2_0.idd
eppy/resources/iddfiles/Energy+V8_0_0.idd
eppy/resources/iddfiles/Energy+V8_1_0.idd
eppy/resources/iddfiles/Energy+V8_3_0.idd
eppy/resources/iddfiles/Energy+V8_4_0.idd
eppy/resources/iddfiles/Energy+V8_5_0.idd
eppy/resources/iddfiles/Energy+V8_6_0.idd
eppy/resources/iddfiles/Energy+V8_7_0.idd
eppy/resources/iddfiles/Energy+V8_8_0.idd
eppy/resources/iddfiles/Energy+V8_9_0.idd
eppy/resources/iddfiles/Energy+V9_0_1.idd
eppy/resources/iddfiles/Energy+V9_2_0.idd
eppy/resources/idffiles/V8_0_0/5ZoneSupRetPlenRAB.idf
eppy/resources/idffiles/V8_0_0/5ZoneWaterLoopHeatPump.idf
eppy-0.5.69.dist-info/METADATA
eppy-0.5.69.dist-info/WHEEL
eppy-0.5.69.dist-info/licenses/LICENSE
eppy-0.5.69.dist-info/RECORD
