Metadata-Version: 2.4
Name: eppy
Version: 0.5.69
Summary: Scripting language for E+ idf files, and E+ output files
Project-URL: Homepage, https://github.com/santoshphilip/eppy
Project-URL: Repository, https://github.com/santoshphilip/eppy
Project-URL: Issues, https://github.com/santoshphilip/eppy/issues
Author: Santosh Philip
License: MIT License
License-File: LICENSE
Keywords: E+,EnergyPlus,eppy,scripting
Classifier: Development Status :: 5 - Production/Stable
Classifier: Intended Audience :: Developers
Classifier: Intended Audience :: Education
Classifier: Intended Audience :: End Users/Desktop
Classifier: Intended Audience :: Science/Research
Classifier: License :: OSI Approved :: MIT License
Classifier: Natural Language :: English
Requires-Python: >=3.9
Requires-Dist: beautifulsoup4>=4.14.3
Requires-Dist: decorator>=5.2.1
Requires-Dist: future>=1.0.0
Requires-Dist: lxml>=6.0.2
Requires-Dist: munch>=4.0.0
Requires-Dist: nbsphinx>=0.9.8
Requires-Dist: pydot>=4.0.1
Requires-Dist: pyparsing>=3.0.9
Requires-Dist: pytest>=8.4.2
Requires-Dist: six>=1.17.0
Requires-Dist: soupsieve>=2.8.3
Requires-Dist: tinynumpy>=1.2.1
